{"cameraMode":{"drawMode":0,"name":"Shaded","section":"Shading Mode"},"sceneLighting":false,"audioPlay":false,"sceneViewState":{"m_AlwaysRefresh":false,"showFog":true,"showSkybox":false,"showFlares":true,"showImageEffects":true,"showParticleSystems":true,"showVisualEffectGraphs":true,"m_FxEnabled":true},"in2DMode":false,"pivot":{"x":98.0,"y":478.0,"z":-37.0},"rotation":{"x":0.045503634959459308,"y":0.9521162509918213,"z":-0.24545900523662568,"w":0.17650504410266877},"size":15.928910255432129,"orthographic":false}